fms_acceleration_odm/__init__.py
fms_acceleration_odm/callback.py
fms_acceleration_odm/framework_plugin_odm.py
fms_acceleration_odm/patch.py
fms_acceleration_odm/odm/__init__.py
fms_acceleration_odm/odm/auto_categorizer.py
fms_acceleration_odm/odm/dataset.py
fms_acceleration_odm/odm/reward.py
fms_acceleration_odm-0.1.5.dist-info/METADATA
fms_acceleration_odm-0.1.5.dist-info/WHEEL
fms_acceleration_odm-0.1.5.dist-info/RECORD
