Metadata-Version: 2.4
Name: fms-acceleration-odm
Version: 0.1.5
Summary: FMS Acceleration plugin for online data mixing
Author-email: Mehant Kammakomati <mehant.kammakomati2@ibm.com>, Romit Jain <romit@ibm.com>, Padmanabha Venkatagiri Seshadri <seshapad@in.ibm.com>
License: Apache-2.0
Keywords: acceleration,fms-hf-tuning,online-data-mixing
Classifier: Development Status :: 4 - Beta
Classifier: License :: OSI Approved :: Apache Software License
Classifier: Programming Language :: Python :: 3
Classifier: Programming Language :: Python :: 3.11
Requires-Python: ~=3.11
Requires-Dist: datasets==4.*
Requires-Dist: scikit-learn
Requires-Dist: sentence-transformers==5.*
Requires-Dist: torch==2.8.0
Requires-Dist: torchaudio==2.8.0
Requires-Dist: torchdata==0.11.0
Requires-Dist: torchvision==0.23.0
Requires-Dist: transformers<=4.55.4,>=4.55.0
Provides-Extra: dev
Requires-Dist: pytest; extra == 'dev'
